mirroring_flickr/__init__.py
mirroring_flickr/__main__.py
mirroring_flickr/cache_strategy.py
mirroring_flickr/constants.py
mirroring_flickr/flickr.py
mirroring_flickr/parser.py
Flickr_Mirror_Ngoc_Dang-1.0.3.dist-info/LICENSE
Flickr_Mirror_Ngoc_Dang-1.0.3.dist-info/METADATA
Flickr_Mirror_Ngoc_Dang-1.0.3.dist-info/WHEEL
Flickr_Mirror_Ngoc_Dang-1.0.3.dist-info/entry_points.txt
Flickr_Mirror_Ngoc_Dang-1.0.3.dist-info/top_level.txt
Flickr_Mirror_Ngoc_Dang-1.0.3.dist-info/RECORD
