Metadata-Version: 2.1
Name: Flickr-Mirror-Ngoc-Dang
Version: 1.0.3
Summary: A mirror Flickr photostream tool
Home-page: https://github.com/intek-training-jsc/flickr-mirroring-Friendlyngoc
Author: Dang Duc Ngoc
Author-email: ngoc.dang@f4.intek.edu.vn
Maintainer: Dang Duc Ngoc
License: MIT
Platform: UNKNOWN
Requires-Python: >=3.6
Requires-Dist: astroid (==2.4.1)
Requires-Dist: certifi (==2020.4.5.1)
Requires-Dist: chardet (==3.0.4)
Requires-Dist: idna (==2.9)
Requires-Dist: isort (==4.3.21)
Requires-Dist: langdetect (==1.0.8)
Requires-Dist: lazy-object-proxy (==1.4.3)
Requires-Dist: mccabe (==0.6.1)
Requires-Dist: pylint (==2.5.2)
Requires-Dist: requests (==2.23.0)
Requires-Dist: six (==1.14.0)
Requires-Dist: toml (==0.10.0)
Requires-Dist: urllib3 (==1.25.9)
Requires-Dist: wrapt (==1.12.1)
Requires-Dist: typed-ast (==1.4.1) ; implementation_name == "cpython" and python_version < "3.8"
Provides-Extra: dev
Requires-Dist: appdirs (==1.4.3) ; extra == 'dev'
Requires-Dist: attrs (==19.3.0) ; extra == 'dev'
Requires-Dist: cached-property (==1.5.1) ; extra == 'dev'
Requires-Dist: cerberus (==1.3.2) ; extra == 'dev'
Requires-Dist: certifi (==2020.4.5.1) ; extra == 'dev'
Requires-Dist: chardet (==3.0.4) ; extra == 'dev'
Requires-Dist: click (==7.1.2) ; extra == 'dev'
Requires-Dist: colorama (==0.4.3) ; extra == 'dev'
Requires-Dist: distlib (==0.3.0) ; extra == 'dev'
Requires-Dist: idna (==2.9) ; extra == 'dev'
Requires-Dist: orderedmultidict (==1.0.1) ; extra == 'dev'
Requires-Dist: packaging (==20.3) ; extra == 'dev'
Requires-Dist: pathspec (==0.8.0) ; extra == 'dev'
Requires-Dist: pep517 (==0.8.2) ; extra == 'dev'
Requires-Dist: pip-shims (==0.5.2) ; extra == 'dev'
Requires-Dist: pipenv-setup (==3.0.1) ; extra == 'dev'
Requires-Dist: pipfile (==0.0.2) ; extra == 'dev'
Requires-Dist: plette[validation] (==0.2.3) ; extra == 'dev'
Requires-Dist: pyparsing (==2.4.7) ; extra == 'dev'
Requires-Dist: python-dateutil (==2.8.1) ; extra == 'dev'
Requires-Dist: regex (==2020.5.7) ; extra == 'dev'
Requires-Dist: requests (==2.23.0) ; extra == 'dev'
Requires-Dist: requirementslib (==1.5.7) ; extra == 'dev'
Requires-Dist: six (==1.14.0) ; extra == 'dev'
Requires-Dist: toml (==0.10.0) ; extra == 'dev'
Requires-Dist: tomlkit (==0.6.0) ; extra == 'dev'
Requires-Dist: typing (==3.7.4.1) ; extra == 'dev'
Requires-Dist: urllib3 (==1.25.9) ; extra == 'dev'
Requires-Dist: vistir (==0.5.0) ; extra == 'dev'
Requires-Dist: wheel (==0.34.2) ; extra == 'dev'
Requires-Dist: zipp (==3.1.0) ; extra == 'dev'
Requires-Dist: typed-ast (==1.4.1) ; (implementation_name == "cpython" and python_version < "3.8") and extra == 'dev'
Requires-Dist: importlib-metadata (==1.6.0) ; (python_version < "3.8") and extra == 'dev'
Requires-Dist: black (==19.10b0) ; (python_version >= "3.6") and extra == 'dev'
